rps_milea_users/__init__.py
rps_milea_users/admin.py
rps_milea_users/apps.py
rps_milea_users/models.py
rps_milea_users/tests.py
rps_milea_users/locale/de/LC_MESSAGES/django.mo
rps_milea_users/locale/de/LC_MESSAGES/django.po
rps_milea_users/migrations/0001_initial.py
rps_milea_users/migrations/0002_group.py
rps_milea_users/migrations/__init__.py
rps_milea_users/migrations/__pycache__/0001_initial.cpython-311.pyc
rps_milea_users/migrations/__pycache__/0002_group.cpython-311.pyc
rps_milea_users/migrations/__pycache__/__init__.cpython-311.pyc
rps_milea_users-0.1.4.dist-info/METADATA
rps_milea_users-0.1.4.dist-info/WHEEL
rps_milea_users-0.1.4.dist-info/top_level.txt
rps_milea_users-0.1.4.dist-info/RECORD
