Metadata-Version: 2.1
Name: rps-milea-users
Version: 0.1.4
Summary: Django rps.Milea Framework - User Module
Home-page: https://github.com/milea-framework/milea-users
Author: red-pepper-services
Author-email: pypi@schiegg.at
License: MIT
Classifier: Development Status :: 3 - Alpha
Classifier: Framework :: Django
Classifier: Intended Audience :: Developers
Classifier: License :: OSI Approved :: MIT License
Classifier: Operating System :: OS Independent
Classifier: Programming Language :: Python
